odoo/addons/product_code_unique/README.rst
odoo/addons/product_code_unique/__init__.py
odoo/addons/product_code_unique/__manifest__.py
odoo/addons/product_code_unique/hook.py
odoo/addons/product_code_unique/i18n/ca.po
odoo/addons/product_code_unique/i18n/es.po
odoo/addons/product_code_unique/i18n/it.po
odoo/addons/product_code_unique/i18n/product_code_unique.pot
odoo/addons/product_code_unique/models/__init__.py
odoo/addons/product_code_unique/models/product.py
odoo/addons/product_code_unique/readme/CONTRIBUTORS.rst
odoo/addons/product_code_unique/readme/DESCRIPTION.rst
odoo/addons/product_code_unique/readme/USAGE.rst
odoo/addons/product_code_unique/static/description/icon.png
odoo/addons/product_code_unique/static/description/index.html
odoo/addons/product_code_unique/tests/__init__.py
odoo/addons/product_code_unique/tests/test_code_unique.py
odoo13_addon_product_code_unique-13.0.1.0.1.dev12.dist-info/METADATA
odoo13_addon_product_code_unique-13.0.1.0.1.dev12.dist-info/WHEEL
odoo13_addon_product_code_unique-13.0.1.0.1.dev12.dist-info/top_level.txt
odoo13_addon_product_code_unique-13.0.1.0.1.dev12.dist-info/RECORD
